{
  "uid" : "c53601eebe29435e",
  "name" : "72MP VideoIzleMaxiPlayerYukaridanAsagiSwipe",
  "historyId" : "1df41b65815bdee86984570d29f9b069",
  "time" : {
    "start" : 1560912351537,
    "stop" : 1560912534972,
    "duration" : 183435
  },
  "status" : "passed",
  "flaky" : false,
  "newFailed" : false,
  "beforeStages" : [ ],
  "testStage" : {
    "status" : "passed",
    "steps" : [ {
      "name" : "before",
      "time" : {
        "start" : 1560912351537,
        "stop" : 1560912351539,
        "duration" : 2
      },
      "status" : "passed",
      "steps" : [ ],
      "attachments" : [ ],
      "parameters" : [ ],
      "stepsCount" : 0,
      "attachmentsCount" : 0,
      "shouldDisplayMessage" : false,
      "hasContent" : false
    }, {
      "name" : "before",
      "time" : {
        "start" : 1560912351539,
        "stop" : 1560912351539,
        "duration" : 0
      },
      "status" : "passed",
      "steps" : [ ],
      "attachments" : [ ],
      "parameters" : [ ],
      "stepsCount" : 0,
      "attachmentsCount" : 0,
      "shouldDisplayMessage" : false,
      "hasContent" : false
    }, {
      "name" : "before",
      "time" : {
        "start" : 1560912351539,
        "stop" : 1560912351540,
        "duration" : 1
      },
      "status" : "passed",
      "steps" : [ ],
      "attachments" : [ ],
      "parameters" : [ ],
      "stepsCount" : 0,
      "attachmentsCount" : 0,
      "shouldDisplayMessage" : false,
      "hasContent" : false
    }, {
      "name" : "before",
      "time" : {
        "start" : 1560912351540,
        "stop" : 1560912351540,
        "duration" : 0
      },
      "status" : "passed",
      "steps" : [ ],
      "attachments" : [ ],
      "parameters" : [ ],
      "stepsCount" : 0,
      "attachmentsCount" : 0,
      "shouldDisplayMessage" : false,
      "hasContent" : false
    }, {
      "name" : "Given  android device A",
      "time" : {
        "start" : 1560912351540,
        "stop" : 1560912351541,
        "duration" : 1
      },
      "status" : "passed",
      "steps" : [ ],
      "attachments" : [ ],
      "parameters" : [ ],
      "stepsCount" : 0,
      "attachmentsCount" : 0,
      "shouldDisplayMessage" : false,
      "hasContent" : false
    }, {
      "name" : "When  I start fizy application",
      "time" : {
        "start" : 1560912351541,
        "stop" : 1560912357097,
        "duration" : 5556
      },
      "status" : "passed",
      "steps" : [ ],
      "attachments" : [ ],
      "parameters" : [ ],
      "stepsCount" : 0,
      "attachmentsCount" : 0,
      "shouldDisplayMessage" : false,
      "hasContent" : false
    }, {
      "name" : "And  I log in as any nonpremium user without download package",
      "time" : {
        "start" : 1560912357097,
        "stop" : 1560912443934,
        "duration" : 86837
      },
      "status" : "passed",
      "steps" : [ ],
      "attachments" : [ ],
      "parameters" : [ ],
      "stepsCount" : 0,
      "attachmentsCount" : 0,
      "shouldDisplayMessage" : false,
      "hasContent" : false
    }, {
      "name" : "And  I see home page",
      "time" : {
        "start" : 1560912443934,
        "stop" : 1560912444119,
        "duration" : 185
      },
      "status" : "passed",
      "steps" : [ ],
      "attachments" : [ ],
      "parameters" : [ ],
      "stepsCount" : 0,
      "attachmentsCount" : 0,
      "shouldDisplayMessage" : false,
      "hasContent" : false
    }, {
      "name" : "When  I go to search page and type \"Tarkan\" and swipe to first video title",
      "time" : {
        "start" : 1560912444119,
        "stop" : 1560912467355,
        "duration" : 23236
      },
      "status" : "passed",
      "steps" : [ ],
      "attachments" : [ ],
      "parameters" : [ ],
      "stepsCount" : 0,
      "attachmentsCount" : 0,
      "shouldDisplayMessage" : false,
      "hasContent" : false
    }, {
      "name" : "And  I click first video title",
      "time" : {
        "start" : 1560912467356,
        "stop" : 1560912467730,
        "duration" : 374
      },
      "status" : "passed",
      "steps" : [ ],
      "attachments" : [ ],
      "parameters" : [ ],
      "stepsCount" : 0,
      "attachmentsCount" : 0,
      "shouldDisplayMessage" : false,
      "hasContent" : false
    }, {
      "name" : "Then  I see player page",
      "time" : {
        "start" : 1560912467730,
        "stop" : 1560912488398,
        "duration" : 20668
      },
      "status" : "passed",
      "steps" : [ ],
      "attachments" : [ ],
      "parameters" : [ ],
      "stepsCount" : 0,
      "attachmentsCount" : 0,
      "shouldDisplayMessage" : false,
      "hasContent" : false
    }, {
      "name" : "And  I click pause button",
      "time" : {
        "start" : 1560912488399,
        "stop" : 1560912529846,
        "duration" : 41447
      },
      "status" : "passed",
      "steps" : [ ],
      "attachments" : [ ],
      "parameters" : [ ],
      "stepsCount" : 0,
      "attachmentsCount" : 0,
      "shouldDisplayMessage" : false,
      "hasContent" : false
    }, {
      "name" : "And  I save song name text as the video title",
      "time" : {
        "start" : 1560912529846,
        "stop" : 1560912530026,
        "duration" : 180
      },
      "status" : "passed",
      "steps" : [ ],
      "attachments" : [ ],
      "parameters" : [ ],
      "stepsCount" : 0,
      "attachmentsCount" : 0,
      "shouldDisplayMessage" : false,
      "hasContent" : false
    }, {
      "name" : "When  I swipe center of song name to down",
      "time" : {
        "start" : 1560912530026,
        "stop" : 1560912531887,
        "duration" : 1861
      },
      "status" : "passed",
      "steps" : [ ],
      "attachments" : [ ],
      "parameters" : [ ],
      "stepsCount" : 0,
      "attachmentsCount" : 0,
      "shouldDisplayMessage" : false,
      "hasContent" : false
    }, {
      "name" : "Then  I see mini player element",
      "time" : {
        "start" : 1560912531887,
        "stop" : 1560912532686,
        "duration" : 799
      },
      "status" : "passed",
      "steps" : [ ],
      "attachments" : [ ],
      "parameters" : [ ],
      "stepsCount" : 0,
      "attachmentsCount" : 0,
      "shouldDisplayMessage" : false,
      "hasContent" : false
    }, {
      "name" : "Then  I save media name text as the music name",
      "time" : {
        "start" : 1560912532687,
        "stop" : 1560912532806,
        "duration" : 119
      },
      "status" : "passed",
      "steps" : [ ],
      "attachments" : [ ],
      "parameters" : [ ],
      "stepsCount" : 0,
      "attachmentsCount" : 0,
      "shouldDisplayMessage" : false,
      "hasContent" : false
    }, {
      "name" : "Then  I verify the music name equals the video title",
      "time" : {
        "start" : 1560912532806,
        "stop" : 1560912532806,
        "duration" : 0
      },
      "status" : "passed",
      "steps" : [ ],
      "attachments" : [ ],
      "parameters" : [ ],
      "stepsCount" : 0,
      "attachmentsCount" : 0,
      "shouldDisplayMessage" : false,
      "hasContent" : false
    }, {
      "name" : "When  I click mini player",
      "time" : {
        "start" : 1560912532807,
        "stop" : 1560912532976,
        "duration" : 169
      },
      "status" : "passed",
      "steps" : [ ],
      "attachments" : [ ],
      "parameters" : [ ],
      "stepsCount" : 0,
      "attachmentsCount" : 0,
      "shouldDisplayMessage" : false,
      "hasContent" : false
    }, {
      "name" : "Then  I see player page",
      "time" : {
        "start" : 1560912532976,
        "stop" : 1560912534659,
        "duration" : 1683
      },
      "status" : "passed",
      "steps" : [ ],
      "attachments" : [ ],
      "parameters" : [ ],
      "stepsCount" : 0,
      "attachmentsCount" : 0,
      "shouldDisplayMessage" : false,
      "hasContent" : false
    }, {
      "name" : "after",
      "time" : {
        "start" : 1560912534659,
        "stop" : 1560912534659,
        "duration" : 0
      },
      "status" : "passed",
      "steps" : [ ],
      "attachments" : [ ],
      "parameters" : [ ],
      "stepsCount" : 0,
      "attachmentsCount" : 0,
      "shouldDisplayMessage" : false,
      "hasContent" : false
    }, {
      "name" : "after",
      "time" : {
        "start" : 1560912534660,
        "stop" : 1560912534660,
        "duration" : 0
      },
      "status" : "passed",
      "steps" : [ ],
      "attachments" : [ ],
      "parameters" : [ ],
      "stepsCount" : 0,
      "attachmentsCount" : 0,
      "shouldDisplayMessage" : false,
      "hasContent" : false
    }, {
      "name" : "after",
      "time" : {
        "start" : 1560912534660,
        "stop" : 1560912534660,
        "duration" : 0
      },
      "status" : "passed",
      "steps" : [ ],
      "attachments" : [ ],
      "parameters" : [ ],
      "stepsCount" : 0,
      "attachmentsCount" : 0,
      "shouldDisplayMessage" : false,
      "hasContent" : false
    }, {
      "name" : "after",
      "time" : {
        "start" : 1560912534660,
        "stop" : 1560912534660,
        "duration" : 0
      },
      "status" : "passed",
      "steps" : [ ],
      "attachments" : [ ],
      "parameters" : [ ],
      "stepsCount" : 0,
      "attachmentsCount" : 0,
      "shouldDisplayMessage" : false,
      "hasContent" : false
    }, {
      "name" : "after",
      "time" : {
        "start" : 1560912534660,
        "stop" : 1560912534820,
        "duration" : 160
      },
      "status" : "passed",
      "steps" : [ ],
      "attachments" : [ ],
      "parameters" : [ ],
      "stepsCount" : 0,
      "attachmentsCount" : 0,
      "shouldDisplayMessage" : false,
      "hasContent" : false
    }, {
      "name" : "after",
      "time" : {
        "start" : 1560912534820,
        "stop" : 1560912534820,
        "duration" : 0
      },
      "status" : "passed",
      "steps" : [ ],
      "attachments" : [ ],
      "parameters" : [ ],
      "stepsCount" : 0,
      "attachmentsCount" : 0,
      "shouldDisplayMessage" : false,
      "hasContent" : false
    }, {
      "name" : "after",
      "time" : {
        "start" : 1560912534820,
        "stop" : 1560912534820,
        "duration" : 0
      },
      "status" : "passed",
      "steps" : [ ],
      "attachments" : [ ],
      "parameters" : [ ],
      "stepsCount" : 0,
      "attachmentsCount" : 0,
      "shouldDisplayMessage" : false,
      "hasContent" : false
    }, {
      "name" : "after",
      "time" : {
        "start" : 1560912534820,
        "stop" : 1560912534971,
        "duration" : 151
      },
      "status" : "passed",
      "steps" : [ ],
      "attachments" : [ ],
      "parameters" : [ ],
      "stepsCount" : 0,
      "attachmentsCount" : 0,
      "shouldDisplayMessage" : false,
      "hasContent" : false
    }, {
      "name" : "after",
      "time" : {
        "start" : 1560912534971,
        "stop" : 1560912534972,
        "duration" : 1
      },
      "status" : "passed",
      "steps" : [ ],
      "attachments" : [ ],
      "parameters" : [ ],
      "stepsCount" : 0,
      "attachmentsCount" : 0,
      "shouldDisplayMessage" : false,
      "hasContent" : false
    } ],
    "attachments" : [ ],
    "parameters" : [ ],
    "stepsCount" : 28,
    "attachmentsCount" : 0,
    "shouldDisplayMessage" : false,
    "hasContent" : true
  },
  "afterStages" : [ ],
  "labels" : [ {
    "name" : "feature",
    "value" : "Player with Non Premium Package"
  }, {
    "name" : "story",
    "value" : "72MP VideoIzleMaxiPlayerYukaridanAsagiSwipe"
  }, {
    "name" : "tag",
    "value" : "android"
  }, {
    "name" : "tag",
    "value" : "playerFeature"
  }, {
    "name" : "tag",
    "value" : "nonPremiumUser"
  }, {
    "name" : "tag",
    "value" : "notDownloadPackage"
  }, {
    "name" : "tag",
    "value" : "regression"
  }, {
    "name" : "tag",
    "value" : "rerun"
  }, {
    "name" : "host",
    "value" : "localhost"
  }, {
    "name" : "package",
    "value" : "Player with Non Premium Package"
  }, {
    "name" : "suite",
    "value" : "Player with Non Premium Package"
  }, {
    "name" : "testClass",
    "value" : "72MP VideoIzleMaxiPlayerYukaridanAsagiSwipe"
  }, {
    "name" : "thread",
    "value" : "android/Login with Password/Non Premium Package/Without Download Package/nonPremiumPackagewithPlayer2"
  }, {
    "name" : "resultFormat",
    "value" : "allure2"
  } ],
  "parameters" : [ ],
  "links" : [ ],
  "hidden" : false,
  "retry" : false,
  "extra" : {
    "severity" : "normal",
    "retries" : [ ],
    "categories" : [ ],
    "tags" : [ "playerFeature", "regression", "android", "notDownloadPackage", "nonPremiumUser", "rerun" ]
  },
  "source" : "c53601eebe29435e.json",
  "parameterValues" : [ ]
}